miblab_data/__init__.py
miblab_data/osf.py
miblab_data/tristan.py
miblab_data/utils.py
miblab_data/xnat.py
miblab_data/zenodo.py
miblab_data-0.0.6.dist-info/licenses/LICENSE
miblab_data-0.0.6.dist-info/METADATA
miblab_data-0.0.6.dist-info/WHEEL
miblab_data-0.0.6.dist-info/top_level.txt
miblab_data-0.0.6.dist-info/RECORD
