Metadata-Version: 2.4
Name: miblab-data
Version: 0.0.6
Summary: A python API for miblab data
Author-email: Steven Sourbron <s.sourbron@sheffield.ac.uk>, Kevin Teh <k.teh@sheffield.ac.uk>
License-Expression: Apache-2.0
Project-URL: Homepage, https://miblab.org/
Project-URL: Source Code, https://github.com/openmiblab/docs-miblab-data
Keywords: python,medical imaging,MRI,XNAT
Classifier: Development Status :: 3 - Alpha
Classifier: Intended Audience :: Developers
Classifier: Intended Audience :: Science/Research
Classifier: Topic :: Scientific/Engineering
Classifier: Operating System :: OS Independent
Classifier: Programming Language :: Python
Classifier: Programming Language :: Python :: 3
License-File: LICENSE
Requires-Dist: importlib-resources>=1.1.0
Requires-Dist: tqdm
Requires-Dist: requests
Requires-Dist: osfclient
Requires-Dist: pydicom
Requires-Dist: dicom2nifti==2.3.4
Dynamic: license-file
